cmem_plugin_salesforce/__init__.py
cmem_plugin_salesforce/helper/__init__.py
cmem_plugin_salesforce/workflow/__init__.py
cmem_plugin_salesforce/workflow/operations.py
cmem_plugin_salesforce/workflow/soql_query.py
cmem_plugin_salesforce-2.1.1.dist-info/METADATA
cmem_plugin_salesforce-2.1.1.dist-info/WHEEL
cmem_plugin_salesforce-2.1.1.dist-info/licenses/LICENSE
cmem_plugin_salesforce-2.1.1.dist-info/RECORD
