Metadata-Version: 2.4
Name: cmem-plugin-salesforce
Version: 2.1.1
Summary: Send or receive data from your organization´s Salesforce account.
License: Apache-2.0
License-File: LICENSE
Keywords: eccenca Corporate Memory,plugin,Salesforce
Author: eccenca GmbH
Author-email: cmempy-developer@eccenca.com
Requires-Python: >=3.13,<4.0
Classifier: Development Status :: 4 - Beta
Classifier: Environment :: Plugins
Classifier: License :: OSI Approved :: Apache Software License
Classifier: Programming Language :: Python :: 3
Classifier: Programming Language :: Python :: 3.13
Classifier: Programming Language :: Python :: 3.14
Requires-Dist: cmem-plugin-base (>=4.15.0,<5.0.0)
Requires-Dist: simple-salesforce (>=1.11.6,<2.0.0)
Project-URL: Homepage, https://github.com/eccenca/cmem-plugin-salesforce
